{
  "skill_id": "ovos-skill-fallback-unknown.openvoiceos",
  "source": "https://github.com/OpenVoiceOS/skill-ovos-fallback-unknown",
  "package_name": "ovos-skill-fallback-unknown",
  "extra_plugins": {
    "core": [],
    "PHAL": [],
    "listener": [],
    "audio": [],
    "media": [],
    "gui": []
  },
  "icon": "https://raw.githack.com/FortAwesome/Font-Awesome/master/svgs/solid/question.svg",
  "name": "Unknown Handler",
  "description": "Capture unrecognized Utterances. OpenVoiceOS doesn't know how to do or answer everything (yet). This fallback is how the assistant lets you know that, unfortunately, it can't help with what you said.",
  "category": "Configuration",
  "tags": [
    "fallback",
    "unknown",
    "system"
  ],
  "images": []
}
